server/__init__.py
server/server.py
server/server_class.py
server/server_functions.py
server/server_gui_classes.py
server/server_gui_dialog_classes.py
server/server_storage_class.py
server/common/__init__.py
server/common/custom_exceptions.py
server/common/decos.py
server/common/descriptors.py
server/common/metaclasses.py
server/common/utils.py
server/common/variables.py
server/logs/__init__.py
server/logs/server_log_config.py
helens_messenger_server-0.0.1.dist-info/METADATA
helens_messenger_server-0.0.1.dist-info/WHEEL
helens_messenger_server-0.0.1.dist-info/top_level.txt
helens_messenger_server-0.0.1.dist-info/RECORD
